<?xml version="1.0" encoding="utf-8"?>
<!--
    Copyright (c) 2019-2020 The Evolution X Project

    Licensed under the Apache License, Version 2.0 (the "License");
    you may not use this file except in compliance with the License.
    You may obtain a copy of the License at

        http://www.apache.org/licenses/LICENSE-2.0

    Unless required by applicable law or agreed to in writing, software
    distributed under the License is distributed on an "AS IS" BASIS,
    WITHOUT WARRANTIES OR CONDITIONS OF ANY KIND, either express or implied.
    See the License for the specific language governing permissions and
    limitations under the License.
-->
<resources xmlns:xliff="urn:oasis:names:tc:xliff:document:1.2">
    <!-- Minutes displayed in words on the typographic clock face. [CHAR LIMIT=20] -->
    <string-array name="type_clock_minutes_alt">
        <item>En punto</item>
        <item>y una</item>
        <item>y dos</item>
        <item>y tres</item>
        <item>y cuatro</item>
        <item>y cinco</item>
        <item>y seis</item>
        <item>y siete</item>
        <item>y ocho</item>
        <item>y nueve</item>
        <item>y diez</item>
        <item>y once</item>
        <item>y doce</item>
        <item>y trece</item>
        <item>y catorce</item>
        <item>y cuarto</item>
        <item>y dieciséis</item>
        <item>y diecisiete</item>
        <item>y dieciocho</item>
        <item>y diecinueve</item>
        <item>y veinte</item>
        <item>y veintiuno</item>
        <item>y veintidós</item>
        <item>y veintitrés</item>
        <item>y veinticuatro</item>
        <item>y veinticinco</item>
        <item>y veintiséis</item>
        <item>y veintisiete</item>
        <item>y veintiocho</item>
        <item>y veintinueve</item>
        <item>y media</item>
        <item>treinta y uno</item>
        <item>treinta y dos</item>
        <item>treinta y tres</item>
        <item>treinta y cuatro</item>
        <item>treinta y cinco</item>
        <item>treinta y seis</item>
        <item>treinta y siete</item>
        <item>treinta y ocho</item>
        <item>treinta y nueve</item>
        <item>cuarenta</item>
        <item>cuarenta y uno</item>
        <item>cuarenta y dos</item>
        <item>cuarenta y tres</item>
        <item>cuarenta y cuatro</item>
        <item>cuarenta y cinco</item>
        <item>cuarenta y seis</item>
        <item>cuarenta y siete</item>
        <item>cuarenta y ocho</item>
        <item>cuarenta y nueve</item>
        <item>cincuenta</item>
        <item>cincuenta y uno</item>
        <item>cincuenta y dos</item>
        <item>cincuenta y tres</item>
        <item>cincuenta y cuatro</item>
        <item>cincuenta y cinco</item>
        <item>cincuenta y seis</item>
        <item>cincuenta y siete</item>
        <item>cincuenta y ocho</item>
        <item>cincuenta y nueve</item>
    </string-array>
</resources>
